ALU/Xor/xor1x1.v
`timescale 1ns / 1ps

module xor1(
  input a,
  input b,
  output ans
  );

  xor g1(ans,a,b);  

endmodule

ALU/Xor/xor32x1.v
`timescale 1ns / 1ps

module xor32(
  input signed [31:0]a,
  input signed [31:0]b,
  output signed [31:0]ans
  );

  genvar i;

  generate for(i=0; i<32; i=i+1) 
  begin
    xor1 g1(a[i],b[i],ans[i]);
  end
  endgenerate  
endmodule

ALU/Xor/xor32_test.v
`timescale 1ns / 1ps

module Xor_test;
  reg signed [31:0]a;
  reg signed [31:0]b;

  wire signed [31:0]ans;

  xor32 uut(
    .a(a),
    .b(b),
    .ans(ans)
  );

  initial begin
		$dumpfile("Xor_test.vcd");
    $dumpvars(0,Xor_test);
		a = 32'b0;
		b = 32'b0;

		#100;

		#20 a=32'b1011;b=32'b0100;
    #20 a=32'b1011;b=32'b1100;
    #20 a=-32'b1011;b=32'b1100;
    #20 a=32'b1001;b=32'b1001;
    #20 a=-32'd2;b=32'd13;
    #20 a=-32'd2;b=-32'd13;
    #20 a=32'b1001;b=32'b1001;
	end
	
  initial 
		$monitor("a=%b b=%b ans=%b\n",a,b,ans);
endmodule

ALU/Xor/Xor_test.vcd
$date
	Wed Feb  3 17:08:04 2021
$end
$version
	Icarus Verilog
$end
$timescale
	1ps
$end
$scope module Xor_test $end
$var wire 32 ! ans [31:0] $end
$var reg 32 " a [31:0] $end
$var reg 32 # b [31:0] $end
$scope module uut $end
$var wire 32 $ a [31:0] $end
$var wire 32 % b [31:0] $end
$var wire 32 & ans [31:0] $end
$scope begin genblk1[0] $end
$scope module g1 $end
$var wire 1 ' a $end
$var wire 1 ( ans $end
$var wire 1 ) b $end
$upscope $end
$upscope $end
$scope begin genblk1[1] $end
$scope module g1 $end
$var wire 1 * a $end
$var wire 1 + ans $end
$var wire 1 , b $end
$upscope $end
$upscope $end
$scope begin genblk1[2] $end
$scope module g1 $end
$var wire 1 - a $end
$var wire 1 . ans $end
$var wire 1 / b $end
$upscope $end
$upscope $end
$scope begin genblk1[3] $end
$scope module g1 $end
$var wire 1 0 a $end
$var wire 1 1 ans $end
$var wire 1 2 b $end
$upscope $end
$upscope $end
$scope begin genblk1[4] $end
$scope module g1 $end
$var wire 1 3 a $end
$var wire 1 4 ans $end
$var wire 1 5 b $end
$upscope $end
$upscope $end
$scope begin genblk1[5] $end
$scope module g1 $end
$var wire 1 6 a $end
$var wire 1 7 ans $end
$var wire 1 8 b $end
$upscope $end
$upscope $end
$scope begin genblk1[6] $end
$scope module g1 $end
$var wire 1 9 a $end
$var wire 1 : ans $end
$var wire 1 ; b $end
$upscope $end
$upscope $end
$scope begin genblk1[7] $end
$scope module g1 $end
$var wire 1 < a $end
$var wire 1 = ans $end
$var wire 1 > b $end
$upscope $end
$upscope $end
$scope begin genblk1[8] $end
$scope module g1 $end
$var wire 1 ? a $end
$var wire 1 @ ans $end
$var wire 1 A b $end
$upscope $end
$upscope $end
$scope begin genblk1[9] $end
$scope module g1 $end
$var wire 1 B a $end
$var wire 1 C ans $end
$var wire 1 D b $end
$upscope $end
$upscope $end
$scope begin genblk1[10] $end
$scope module g1 $end
$var wire 1 E a $end
$var wire 1 F ans $end
$var wire 1 G b $end
$upscope $end
$upscope $end
$scope begin genblk1[11] $end
$scope module g1 $end
$var wire 1 H a $end
$var wire 1 I ans $end
$var wire 1 J b $end
$upscope $end
$upscope $end
$scope begin genblk1[12] $end
$scope module g1 $end
$var wire 1 K a $end
$var wire 1 L ans $end
$var wire 1 M b $end
$upscope $end
$upscope $end
$scope begin genblk1[13] $end
$scope module g1 $end
$var wire 1 N a $end
$var wire 1 O ans $end
$var wire 1 P b $end
$upscope $end
$upscope $end
$scope begin genblk1[14] $end
$scope module g1 $end
$var wire 1 Q a $end
$var wire 1 R ans $end
$var wire 1 S b $end
$upscope $end
$upscope $end
$scope begin genblk1[15] $end
$scope module g1 $end
$var wire 1 T a $end
$var wire 1 U ans $end
$var wire 1 V b $end
$upscope $end
$upscope $end
$scope begin genblk1[16] $end
$scope module g1 $end
$var wire 1 W a $end
$var wire 1 X ans $end
$var wire 1 Y b $end
$upscope $end
$upscope $end
$scope begin genblk1[17] $end
$scope module g1 $end
$var wire 1 Z a $end
$var wire 1 [ ans $end
$var wire 1 \ b $end
$upscope $end
$upscope $end
$scope begin genblk1[18] $end
$scope module g1 $end
$var wire 1 ] a $end
$var wire 1 ^ ans $end
$var wire 1 _ b $end
$upscope $end
$upscope $end
$scope begin genblk1[19] $end
$scope module g1 $end
$var wire 1 ` a $end
$var wire 1 a ans $end
$var wire 1 b b $end
$upscope $end
$upscope $end
$scope begin genblk1[20] $end
$scope module g1 $end
$var wire 1 c a $end
$var wire 1 d ans $end
$var wire 1 e b $end
$upscope $end
$upscope $end
$scope begin genblk1[21] $end
$scope module g1 $end
$var wire 1 f a $end
$var wire 1 g ans $end
$var wire 1 h b $end
$upscope $end
$upscope $end
$scope begin genblk1[22] $end
$scope module g1 $end
$var wire 1 i a $end
$var wire 1 j ans $end
$var wire 1 k b $end
$upscope $end
$upscope $end
$scope begin genblk1[23] $end
$scope module g1 $end
$var wire 1 l a $end
$var wire 1 m ans $end
$var wire 1 n b $end
$upscope $end
$upscope $end
$scope begin genblk1[24] $end
$scope module g1 $end
$var wire 1 o a $end
$var wire 1 p ans $end
$var wire 1 q b $end
$upscope $end
$upscope $end
$scope begin genblk1[25] $end
$scope module g1 $end
$var wire 1 r a $end
$var wire 1 s ans $end
$var wire 1 t b $end
$upscope $end
$upscope $end
$scope begin genblk1[26] $end
$scope module g1 $end
$var wire 1 u a $end
$var wire 1 v ans $end
$var wire 1 w b $end
$upscope $end
$upscope $end
$scope begin genblk1[27] $end
$scope module g1 $end
$var wire 1 x a $end
$var wire 1 y ans $end
$var wire 1 z b $end
$upscope $end
$upscope $end
$scope begin genblk1[28] $end
$scope module g1 $end
$var wire 1 { a $end
$var wire 1 | ans $end
$var wire 1 } b $end
$upscope $end
$upscope $end
$scope begin genblk1[29] $end
$scope module g1 $end
$var wire 1 ~ a $end
$var wire 1 !" ans $end
$var wire 1 "" b $end
$upscope $end
$upscope $end
$scope begin genblk1[30] $end
$scope module g1 $end
$var wire 1 #" a $end
$var wire 1 $" ans $end
$var wire 1 %" b $end
$upscope $end
$upscope $end
$scope begin genblk1[31] $end
$scope module g1 $end
$var wire 1 &" a $end
$var wire 1 '" ans $end
$var wire 1 (" b $end
$upscope $end
$upscope $end
$upscope $end
$upscope $end
$enddefinitions $end
#0
$dumpvars
0("
0'"
0&"
0%"
0$"
0#"
0""
0!"
0~
0}
0|
0{
0z
0y
0x
0w
0v
0u
0t
0s
0r
0q
0p
0o
0n
0m
0l
0k
0j
0i
0h
0g
0f
0e
0d
0c
0b
0a
0`
0_
0^
0]
0\
0[
0Z
0Y
0X
0W
0V
0U
0T
0S
0R
0Q
0P
0O
0N
0M
0L
0K
0J
0I
0H
0G
0F
0E
0D
0C
0B
0A
0@
0?
0>
0=
0<
0;
0:
09
08
07
06
05
04
03
02
01
00
0/
0.
0-
0,
0+
0*
0)
0(
0'
b0 &
b0 %
b0 $
b0 #
b0 "
b0 !
$end
#120000
1.
1(
1+
b1111 !
b1111 &
11
1/
1'
1*
10
b100 #
b100 %
b1011 "
b1011 $
#140000
b111 !
b111 &
01
12
b1100 #
b1100 %
#160000
0+
0.
11
14
17
1:
1=
1@
1C
1F
1I
1L
1O
1R
1U
1X
1[
1^
1a
1d
1g
1j
1m
1p
1s
1v
1y
1|
1!"
1$"
b11111111111111111111111111111001 !
b11111111111111111111111111111001 &
1'"
0*
1-
00
13
16
19
1<
1?
1B
1E
1H
1K
1N
1Q
1T
1W
1Z
1]
1`
1c
1f
1i
1l
1o
1r
1u
1x
1{
1~
1#"
1&"
b11111111111111111111111111110101 "
b11111111111111111111111111110101 $
#180000
0(
01
04
07
0:
0=
0@
0C
0F
0I
0L
0O
0R
0U
0X
0[
0^
0a
0d
0g
0j
0m
0p
0s
0v
0y
0|
0!"
0$"
b0 !
b0 &
0'"
1)
0/
0-
10
03
06
09
0<
0?
0B
0E
0H
0K
0N
0Q
0T
0W
0Z
0]
0`
0c
0f
0i
0l
0o
0r
0u
0x
0{
0~
0#"
0&"
b1001 #
b1001 %
b1001 "
b1001 $
#200000
1(
1+
14
17
1:
1=
1@
1C
1F
1I
1L
1O
1R
1U
1X
1[
1^
1a
1d
1g
1j
1m
1p
1s
1v
1y
1|
1!"
1$"
b11111111111111111111111111110011 !
b11111111111111111111111111110011 &
1'"
1/
0'
1*
1-
13
16
19
1<
1?
1B
1E
1H
1K
1N
1Q
1T
1W
1Z
1]
1`
1c
1f
1i
1l
1o
1r
1u
1x
1{
1~
1#"
1&"
b1101 #
b1101 %
b11111111111111111111111111111110 "
b11111111111111111111111111111110 $
#220000
0+
1.
11
04
07
0:
0=
0@
0C
0F
0I
0L
0O
0R
0U
0X
0[
0^
0a
0d
0g
0j
0m
0p
0s
0v
0y
0|
0!"
0$"
b1101 !
b1101 &
0'"
1,
0/
02
15
18
1;
1>
1A
1D
1G
1J
1M
1P
1S
1V
1Y
1\
1_
1b
1e
1h
1k
1n
1q
1t
1w
1z
1}
1""
1%"
1("
b11111111111111111111111111110011 #
b11111111111111111111111111110011 %
#240000
01
0(
b0 !
b0 &
0.
0,
12
05
08
0;
0>
0A
0D
0G
0J
0M
0P
0S
0V
0Y
0\
0_
0b
0e
0h
0k
0n
0q
0t
0w
0z
0}
0""
0%"
0("
1'
0*
0-
03
06
09
0<
0?
0B
0E
0H
0K
0N
0Q
0T
0W
0Z
0]
0`
0c
0f
0i
0l
0o
0r
0u
0x
0{
0~
0#"
0&"
b1001 #
b1001 %
b1001 "
b1001 $
