ALU/Add/add1.v
`timescale 1ns / 1ps

module add1(
  input a,
  input b,
  input cin,
  output sum,
  output co);

  xor g1(sum,a,b,cin);
  and g2(k,a,b);
  and g3(l,a,cin);
  and g4(m,b,cin);
  or g5(co,k,l,m);

endmodule

ALU/Add/add32.v
`timescale 1ns / 1ps

module add32(
  input signed [31:0]a,
  input signed [31:0]b,
  output signed [31:0]sum,
  output overflow);

  wire [32:0]c;
  assign c[0]=1'b0;
  
  genvar i;

  generate for(i=0; i<32; i=i+1) 
  begin
    add1 g1(a[i],b[i],c[i],sum[i],c[i+1]);
  end
  endgenerate

  xor g2(overflow,c[31],c[32]);

endmodule

ALU/Add/add32_test.v
`timescale 1ns / 1ps

module add_test;
  reg signed [31:0]a;
  reg signed [31:0]b;

  wire signed [31:0]sum;
  wire overflow;

  add32 uut(
    .a(a),
    .b(b),
    .sum(sum),
    .overflow(overflow)
  );

  initial begin
		$dumpfile("add_test.vcd");
    $dumpvars(0,add_test);
		a = 32'b0;
		b = 32'b0;

		#100;

		#20 a=32'd2147483647;b=32'd1;
    #20 a=-32'd2147483648;b=-32'd1;
    #20 a=32'd23;b=-32'd0;
    #20 a=32'b1001;b=32'b1001;
    #20 a=32'b1001;b=-32'b1001;
    #20 a=-32'd2;b=32'd13;
    #20 a=-32'd2;b=-32'd13;
    #20 a=32'd2;b=-32'd13;
    #20 a=32'd0;b=32'd0;
	end
	
  initial 
		$monitor("a=%d b=%d sum=%d overflow=%d\n",a,b,sum,overflow);
endmodule

ALU/Add/add_test.vcd
$date
	Wed Feb  3 18:39:36 2021
$end
$version
	Icarus Verilog
$end
$timescale
	1ps
$end
$scope module add_test $end
$var wire 32 ! sum [31:0] $end
$var wire 1 " overflow $end
$var reg 32 # a [31:0] $end
$var reg 32 $ b [31:0] $end
$scope module uut $end
$var wire 32 % a [31:0] $end
$var wire 32 & b [31:0] $end
$var wire 1 " overflow $end
$var wire 32 ' sum [31:0] $end
$var wire 33 ( c [32:0] $end
$scope begin genblk1[0] $end
$scope module g1 $end
$var wire 1 ) a $end
$var wire 1 * b $end
$var wire 1 + cin $end
$var wire 1 , co $end
$var wire 1 - k $end
$var wire 1 . l $end
$var wire 1 / m $end
$var wire 1 0 sum $end
$upscope $end
$upscope $end
$scope begin genblk1[1] $end
$scope module g1 $end
$var wire 1 1 a $end
$var wire 1 2 b $end
$var wire 1 3 cin $end
$var wire 1 4 co $end
$var wire 1 5 k $end
$var wire 1 6 l $end
$var wire 1 7 m $end
$var wire 1 8 sum $end
$upscope $end
$upscope $end
$scope begin genblk1[2] $end
$scope module g1 $end
$var wire 1 9 a $end
$var wire 1 : b $end
$var wire 1 ; cin $end
$var wire 1 < co $end
$var wire 1 = k $end
$var wire 1 > l $end
$var wire 1 ? m $end
$var wire 1 @ sum $end
$upscope $end
$upscope $end
$scope begin genblk1[3] $end
$scope module g1 $end
$var wire 1 A a $end
$var wire 1 B b $end
$var wire 1 C cin $end
$var wire 1 D co $end
$var wire 1 E k $end
$var wire 1 F l $end
$var wire 1 G m $end
$var wire 1 H sum $end
$upscope $end
$upscope $end
$scope begin genblk1[4] $end
$scope module g1 $end
$var wire 1 I a $end
$var wire 1 J b $end
$var wire 1 K cin $end
$var wire 1 L co $end
$var wire 1 M k $end
$var wire 1 N l $end
$var wire 1 O m $end
$var wire 1 P sum $end
$upscope $end
$upscope $end
$scope begin genblk1[5] $end
$scope module g1 $end
$var wire 1 Q a $end
$var wire 1 R b $end
$var wire 1 S cin $end
$var wire 1 T co $end
$var wire 1 U k $end
$var wire 1 V l $end
$var wire 1 W m $end
$var wire 1 X sum $end
$upscope $end
$upscope $end
$scope begin genblk1[6] $end
$scope module g1 $end
$var wire 1 Y a $end
$var wire 1 Z b $end
$var wire 1 [ cin $end
$var wire 1 \ co $end
$var wire 1 ] k $end
$var wire 1 ^ l $end
$var wire 1 _ m $end
$var wire 1 ` sum $end
$upscope $end
$upscope $end
$scope begin genblk1[7] $end
$scope module g1 $end
$var wire 1 a a $end
$var wire 1 b b $end
$var wire 1 c cin $end
$var wire 1 d co $end
$var wire 1 e k $end
$var wire 1 f l $end
$var wire 1 g m $end
$var wire 1 h sum $end
$upscope $end
$upscope $end
$scope begin genblk1[8] $end
$scope module g1 $end
$var wire 1 i a $end
$var wire 1 j b $end
$var wire 1 k cin $end
$var wire 1 l co $end
$var wire 1 m k $end
$var wire 1 n l $end
$var wire 1 o m $end
$var wire 1 p sum $end
$upscope $end
$upscope $end
$scope begin genblk1[9] $end
$scope module g1 $end
$var wire 1 q a $end
$var wire 1 r b $end
$var wire 1 s cin $end
$var wire 1 t co $end
$var wire 1 u k $end
$var wire 1 v l $end
$var wire 1 w m $end
$var wire 1 x sum $end
$upscope $end
$upscope $end
$scope begin genblk1[10] $end
$scope module g1 $end
$var wire 1 y a $end
$var wire 1 z b $end
$var wire 1 { cin $end
$var wire 1 | co $end
$var wire 1 } k $end
$var wire 1 ~ l $end
$var wire 1 !" m $end
$var wire 1 "" sum $end
$upscope $end
$upscope $end
$scope begin genblk1[11] $end
$scope module g1 $end
$var wire 1 #" a $end
$var wire 1 $" b $end
$var wire 1 %" cin $end
$var wire 1 &" co $end
$var wire 1 '" k $end
$var wire 1 (" l $end
$var wire 1 )" m $end
$var wire 1 *" sum $end
$upscope $end
$upscope $end
$scope begin genblk1[12] $end
$scope module g1 $end
$var wire 1 +" a $end
$var wire 1 ," b $end
$var wire 1 -" cin $end
$var wire 1 ." co $end
$var wire 1 /" k $end
$var wire 1 0" l $end
$var wire 1 1" m $end
$var wire 1 2" sum $end
$upscope $end
$upscope $end
$scope begin genblk1[13] $end
$scope module g1 $end
$var wire 1 3" a $end
$var wire 1 4" b $end
$var wire 1 5" cin $end
$var wire 1 6" co $end
$var wire 1 7" k $end
$var wire 1 8" l $end
$var wire 1 9" m $end
$var wire 1 :" sum $end
$upscope $end
$upscope $end
$scope begin genblk1[14] $end
$scope module g1 $end
$var wire 1 ;" a $end
$var wire 1 <" b $end
$var wire 1 =" cin $end
$var wire 1 >" co $end
$var wire 1 ?" k $end
$var wire 1 @" l $end
$var wire 1 A" m $end
$var wire 1 B" sum $end
$upscope $end
$upscope $end
$scope begin genblk1[15] $end
$scope module g1 $end
$var wire 1 C" a $end
$var wire 1 D" b $end
$var wire 1 E" cin $end
$var wire 1 F" co $end
$var wire 1 G" k $end
$var wire 1 H" l $end
$var wire 1 I" m $end
$var wire 1 J" sum $end
$upscope $end
$upscope $end
$scope begin genblk1[16] $end
$scope module g1 $end
$var wire 1 K" a $end
$var wire 1 L" b $end
$var wire 1 M" cin $end
$var wire 1 N" co $end
$var wire 1 O" k $end
$var wire 1 P" l $end
$var wire 1 Q" m $end
$var wire 1 R" sum $end
$upscope $end
$upscope $end
$scope begin genblk1[17] $end
$scope module g1 $end
$var wire 1 S" a $end
$var wire 1 T" b $end
$var wire 1 U" cin $end
$var wire 1 V" co $end
$var wire 1 W" k $end
$var wire 1 X" l $end
$var wire 1 Y" m $end
$var wire 1 Z" sum $end
$upscope $end
$upscope $end
$scope begin genblk1[18] $end
$scope module g1 $end
$var wire 1 [" a $end
$var wire 1 \" b $end
$var wire 1 ]" cin $end
$var wire 1 ^" co $end
$var wire 1 _" k $end
$var wire 1 `" l $end
$var wire 1 a" m $end
$var wire 1 b" sum $end
$upscope $end
$upscope $end
$scope begin genblk1[19] $end
$scope module g1 $end
$var wire 1 c" a $end
$var wire 1 d" b $end
$var wire 1 e" cin $end
$var wire 1 f" co $end
$var wire 1 g" k $end
$var wire 1 h" l $end
$var wire 1 i" m $end
$var wire 1 j" sum $end
$upscope $end
$upscope $end
$scope begin genblk1[20] $end
$scope module g1 $end
$var wire 1 k" a $end
$var wire 1 l" b $end
$var wire 1 m" cin $end
$var wire 1 n" co $end
$var wire 1 o" k $end
$var wire 1 p" l $end
$var wire 1 q" m $end
$var wire 1 r" sum $end
$upscope $end
$upscope $end
$scope begin genblk1[21] $end
$scope module g1 $end
$var wire 1 s" a $end
$var wire 1 t" b $end
$var wire 1 u" cin $end
$var wire 1 v" co $end
$var wire 1 w" k $end
$var wire 1 x" l $end
$var wire 1 y" m $end
$var wire 1 z" sum $end
$upscope $end
$upscope $end
$scope begin genblk1[22] $end
$scope module g1 $end
$var wire 1 {" a $end
$var wire 1 |" b $end
$var wire 1 }" cin $end
$var wire 1 ~" co $end
$var wire 1 !# k $end
$var wire 1 "# l $end
$var wire 1 ## m $end
$var wire 1 $# sum $end
$upscope $end
$upscope $end
$scope begin genblk1[23] $end
$scope module g1 $end
$var wire 1 %# a $end
$var wire 1 &# b $end
$var wire 1 '# cin $end
$var wire 1 (# co $end
$var wire 1 )# k $end
$var wire 1 *# l $end
$var wire 1 +# m $end
$var wire 1 ,# sum $end
$upscope $end
$upscope $end
$scope begin genblk1[24] $end
$scope module g1 $end
$var wire 1 -# a $end
$var wire 1 .# b $end
$var wire 1 /# cin $end
$var wire 1 0# co $end
$var wire 1 1# k $end
$var wire 1 2# l $end
$var wire 1 3# m $end
$var wire 1 4# sum $end
$upscope $end
$upscope $end
$scope begin genblk1[25] $end
$scope module g1 $end
$var wire 1 5# a $end
$var wire 1 6# b $end
$var wire 1 7# cin $end
$var wire 1 8# co $end
$var wire 1 9# k $end
$var wire 1 :# l $end
$var wire 1 ;# m $end
$var wire 1 <# sum $end
$upscope $end
$upscope $end
$scope begin genblk1[26] $end
$scope module g1 $end
$var wire 1 =# a $end
$var wire 1 ># b $end
$var wire 1 ?# cin $end
$var wire 1 @# co $end
$var wire 1 A# k $end
$var wire 1 B# l $end
$var wire 1 C# m $end
$var wire 1 D# sum $end
$upscope $end
$upscope $end
$scope begin genblk1[27] $end
$scope module g1 $end
$var wire 1 E# a $end
$var wire 1 F# b $end
$var wire 1 G# cin $end
$var wire 1 H# co $end
$var wire 1 I# k $end
$var wire 1 J# l $end
$var wire 1 K# m $end
$var wire 1 L# sum $end
$upscope $end
$upscope $end
$scope begin genblk1[28] $end
$scope module g1 $end
$var wire 1 M# a $end
$var wire 1 N# b $end
$var wire 1 O# cin $end
$var wire 1 P# co $end
$var wire 1 Q# k $end
$var wire 1 R# l $end
$var wire 1 S# m $end
$var wire 1 T# sum $end
$upscope $end
$upscope $end
$scope begin genblk1[29] $end
$scope module g1 $end
$var wire 1 U# a $end
$var wire 1 V# b $end
$var wire 1 W# cin $end
$var wire 1 X# co $end
$var wire 1 Y# k $end
$var wire 1 Z# l $end
$var wire 1 [# m $end
$var wire 1 \# sum $end
$upscope $end
$upscope $end
$scope begin genblk1[30] $end
$scope module g1 $end
$var wire 1 ]# a $end
$var wire 1 ^# b $end
$var wire 1 _# cin $end
$var wire 1 `# co $end
$var wire 1 a# k $end
$var wire 1 b# l $end
$var wire 1 c# m $end
$var wire 1 d# sum $end
$upscope $end
$upscope $end
$scope begin genblk1[31] $end
$scope module g1 $end
$var wire 1 e# a $end
$var wire 1 f# b $end
$var wire 1 g# cin $end
$var wire 1 h# co $end
$var wire 1 i# k $end
$var wire 1 j# l $end
$var wire 1 k# m $end
$var wire 1 l# sum $end
$upscope $end
$upscope $end
$upscope $end
$upscope $end
$enddefinitions $end
#0
$dumpvars
0l#
0k#
0j#
0i#
0h#
0g#
0f#
0e#
0d#
0c#
0b#
0a#
0`#
0_#
0^#
0]#
0\#
0[#
0Z#
0Y#
0X#
0W#
0V#
0U#
0T#
0S#
0R#
0Q#
0P#
0O#
0N#
0M#
0L#
0K#
0J#
0I#
0H#
0G#
0F#
0E#
0D#
0C#
0B#
0A#
0@#
0?#
0>#
0=#
0<#
0;#
0:#
09#
08#
07#
06#
05#
04#
03#
02#
01#
00#
0/#
0.#
0-#
0,#
0+#
0*#
0)#
0(#
0'#
0&#
0%#
0$#
0##
0"#
0!#
0~"
0}"
0|"
0{"
0z"
0y"
0x"
0w"
0v"
0u"
0t"
0s"
0r"
0q"
0p"
0o"
0n"
0m"
0l"
0k"
0j"
0i"
0h"
0g"
0f"
0e"
0d"
0c"
0b"
0a"
0`"
0_"
0^"
0]"
0\"
0["
0Z"
0Y"
0X"
0W"
0V"
0U"
0T"
0S"
0R"
0Q"
0P"
0O"
0N"
0M"
0L"
0K"
0J"
0I"
0H"
0G"
0F"
0E"
0D"
0C"
0B"
0A"
0@"
0?"
0>"
0="
0<"
0;"
0:"
09"
08"
07"
06"
05"
04"
03"
02"
01"
00"
0/"
0."
0-"
0,"
0+"
0*"
0)"
0("
0'"
0&"
0%"
0$"
0#"
0""
0!"
0~
0}
0|
0{
0z
0y
0x
0w
0v
0u
0t
0s
0r
0q
0p
0o
0n
0m
0l
0k
0j
0i
0h
0g
0f
0e
0d
0c
0b
0a
0`
0_
0^
0]
0\
0[
0Z
0Y
0X
0W
0V
0U
0T
0S
0R
0Q
0P
0O
0N
0M
0L
0K
0J
0I
0H
0G
0F
0E
0D
0C
0B
0A
0@
0?
0>
0=
0<
0;
0:
09
08
07
06
05
04
03
02
01
00
0/
0.
0-
0,
0+
0*
0)
b0 (
b0 '
b0 &
b0 %
b0 $
b0 #
0"
b0 !
$end
#120000
1"
1l#
1g#
1`#
1b#
1_#
1X#
1Z#
1W#
1P#
1R#
1O#
1H#
1J#
1G#
1@#
1B#
1?#
18#
1:#
17#
10#
12#
1/#
1(#
1*#
1'#
1~"
1"#
1}"
1v"
1x"
1u"
1n"
1p"
1m"
1f"
1h"
1e"
1^"
1`"
1]"
1V"
1X"
1U"
1N"
1P"
1M"
1F"
1H"
1E"
1>"
1@"
1="
16"
18"
15"
1."
10"
1-"
1&"
1("
1%"
1|
1~
1{
1t
1v
1s
1l
1n
1k
1d
1f
1c
1\
1^
1[
1T
1V
1S
1L
1N
1K
1D
1F
1C
1<
1>
1;
14
16
13
b11111111111111111111111111111110 (
1,
1-
08
0@
0H
0P
0X
0`
0h
0p
0x
0""
0*"
02"
0:"
0B"
0J"
0R"
0Z"
0b"
0j"
0r"
0z"
0$#
0,#
04#
0<#
0D#
0L#
0T#
0\#
b10000000000000000000000000000000 !
b10000000000000000000000000000000 '
0d#
1*
1)
11
19
1A
1I
1Q
1Y
1a
1i
1q
1y
1#"
1+"
13"
1;"
1C"
1K"
1S"
1["
1c"
1k"
1s"
1{"
1%#
1-#
15#
1=#
1E#
1M#
1U#
1]#
b1 $
b1 &
b1111111111111111111111111111111 #
b1111111111111111111111111111111 %
#140000
0l#
0g#
0`#
1d#
0_#
0X#
1\#
0W#
0P#
1T#
0O#
0H#
1L#
0G#
0@#
1D#
0?#
08#
1<#
07#
00#
14#
0/#
0(#
1,#
0'#
0~"
1$#
0}"
0v"
1z"
0u"
0n"
1r"
0m"
0f"
1j"
0e"
0^"
1b"
0]"
0V"
1Z"
0U"
0N"
1R"
0M"
0F"
1J"
0E"
0>"
1B"
0="
06"
1:"
05"
0."
12"
0-"
0&"
1*"
0%"
0|
1""
0{
0t
1x
0s
0l
1p
0k
0d
1h
0c
0\
1`
0[
0T
1X
0S
0L
1P
0K
0D
1H
0C
0<
1@
0;
04
18
1"
03
0,
b100000000000000000000000000000000 (
1h#
07
0?
0G
0O
0W
0_
0g
0o
0w
0!"
0)"
01"
09"
0A"
0I"
0Q"
0Y"
0a"
0i"
0q"
0y"
0##
0+#
03#
0;#
0C#
0K#
0S#
0[#
0c#
0k#
b1111111111111111111111111111111 !
b1111111111111111111111111111111 '
10
0-
06
0>
0F
0N
0V
0^
0f
0n
0v
0~
0("
00"
08"
0@"
0H"
0P"
0X"
0`"
0h"
0p"
0x"
0"#
0*#
02#
0:#
0B#
0J#
0R#
0Z#
0b#
1i#
0j#
12
1:
1B
1J
1R
1Z
1b
1j
1r
1z
1$"
1,"
14"
1<"
1D"
1L"
1T"
1\"
1d"
1l"
1t"
1|"
1&#
1.#
16#
1>#
1F#
1N#
1V#
1^#
1f#
0)
01
09
0A
0I
0Q
0Y
0a
0i
0q
0y
0#"
0+"
03"
0;"
0C"
0K"
0S"
0["
0c"
0k"
0s"
0{"
0%#
0-#
05#
0=#
0E#
0M#
0U#
0]#
1e#
b11111111111111111111111111111111 $
b11111111111111111111111111111111 &
b10000000000000000000000000000000 #
b10000000000000000000000000000000 %
#160000
0"
b0 (
0h#
0H
0X
0`
0h
0p
0x
0""
0*"
02"
0:"
0B"
0J"
0R"
0Z"
0b"
0j"
0r"
0z"
0$#
0,#
04#
0<#
0D#
0L#
0T#
0\#
b10111 !
b10111 '
0d#
0i#
0*
02
0:
0B
0J
0R
0Z
0b
0j
0r
0z
0$"
0,"
04"
0<"
0D"
0L"
0T"
0\"
0d"
0l"
0t"
0|"
0&#
0.#
06#
0>#
0F#
0N#
0V#
0^#
0f#
1)
11
19
1I
0e#
b0 $
b0 &
b10111 #
b10111 %
#180000
13
1K
1,
b10010 (
1D
00
1-
18
0@
1E
b10010 !
b10010 '
1P
1*
1B
01
09
1A
0I
b1001 $
b1001 &
b1001 #
b1001 %
#200000
1h#
0"
1k#
1g#
1`#
1c#
1_#
1X#
1[#
1W#
1P#
1S#
1O#
1H#
1K#
1G#
1@#
1C#
1?#
18#
1;#
17#
10#
13#
1/#
1(#
1+#
1'#
1~"
1##
1}"
1v"
1y"
1u"
1n"
1q"
1m"
1f"
1i"
1e"
1^"
1a"
1]"
1V"
1Y"
1U"
1N"
1Q"
1M"
1F"
1I"
1E"
1>"
1A"
1="
16"
19"
15"
1."
11"
1-"
1&"
1)"
1%"
1|
1!"
1{
1t
1w
1s
1l
1o
1k
1d
1g
1c
1\
1F
1_
1C
1[
1<
1T
1?
1W
1;
1K
1S
14
1D
b111111111111111111111111111111110 (
1L
08
17
0@
0H
0E
0P
1O
0X
0`
0h
0p
0x
0""
0*"
02"
0:"
0B"
0J"
0R"
0Z"
0b"
0j"
0r"
0z"
0$#
0,#
04#
0<#
0D#
0L#
0T#
0\#
0d#
b0 !
b0 '
0l#
12
1:
0B
1J
1R
1Z
1b
1j
1r
1z
1$"
1,"
14"
1<"
1D"
1L"
1T"
1\"
1d"
1l"
1t"
1|"
1&#
1.#
16#
1>#
1F#
1N#
1V#
1^#
1f#
b11111111111111111111111111110111 $
b11111111111111111111111111110111 &
#220000
0?
0;
04
18
03
b111111111111111111111111111111000 (
0,
07
1H
1E
1G
0O
0W
0_
0g
0o
0w
0!"
0)"
01"
09"
0A"
0I"
0Q"
0Y"
0a"
0i"
0q"
0y"
0##
0+#
03#
0;#
0C#
0K#
0S#
0[#
0c#
0k#
10
0-
06
b1011 !
b1011 '
0@
1=
0>
1N
1V
1^
1f
1n
1v
1~
1("
10"
18"
1@"
1H"
1P"
1X"
1`"
1h"
1p"
1x"
1"#
1*#
12#
1:#
1B#
1J#
1R#
1Z#
1b#
1j#
02
1B
0J
0R
0Z
0b
0j
0r
0z
0$"
0,"
04"
0<"
0D"
0L"
0T"
0\"
0d"
0l"
0t"
0|"
0&#
0.#
06#
0>#
0F#
0N#
0V#
0^#
0f#
0)
11
19
1I
1Q
1Y
1a
1i
1q
1y
1#"
1+"
13"
1;"
1C"
1K"
1S"
1["
1c"
1k"
1s"
1{"
1%#
1-#
15#
1=#
1E#
1M#
1U#
1]#
1e#
b1101 $
b1101 &
b11111111111111111111111111111110 #
b11111111111111111111111111111110 %
#240000
1N
1K
1D
1>
1F
1;
1C
14
b111111111111111111111111111111100 (
1<
08
15
0@
0=
0H
0E
0G
1P
1M
1O
1X
1U
1W
1`
1]
1_
1h
1e
1g
1p
1m
1o
1x
1u
1w
1""
1}
1!"
1*"
1'"
1)"
12"
1/"
11"
1:"
17"
19"
1B"
1?"
1A"
1J"
1G"
1I"
1R"
1O"
1Q"
1Z"
1W"
1Y"
1b"
1_"
1a"
1j"
1g"
1i"
1r"
1o"
1q"
1z"
1w"
1y"
1$#
1!#
1##
1,#
1)#
1+#
14#
11#
13#
1<#
19#
1;#
1D#
1A#
1C#
1L#
1I#
1K#
1T#
1Q#
1S#
1\#
1Y#
1[#
1d#
1a#
1c#
b11111111111111111111111111110001 !
b11111111111111111111111111110001 '
1l#
1i#
1k#
12
0:
0B
1J
1R
1Z
1b
1j
1r
1z
1$"
1,"
14"
1<"
1D"
1L"
1T"
1\"
1d"
1l"
1t"
1|"
1&#
1.#
16#
1>#
1F#
1N#
1V#
1^#
1f#
b11111111111111111111111111110011 $
b11111111111111111111111111110011 &
#260000
0h#
0"
0k#
0g#
0`#
0c#
0_#
0X#
0[#
0W#
0P#
0S#
0O#
0H#
0K#
0G#
0@#
0C#
0?#
08#
0;#
07#
00#
03#
0/#
0(#
0+#
0'#
0~"
0##
0}"
0v"
0y"
0u"
0n"
0q"
0m"
0f"
0i"
0e"
0^"
0a"
0]"
0V"
0Y"
0U"
0N"
0Q"
0M"
0F"
0I"
0E"
0>"
0A"
0="
06"
09"
05"
0."
01"
0-"
0&"
0)"
0%"
0|
0!"
0{
0t
0w
0s
0l
0o
0k
0d
0g
0c
0\
0_
0[
0T
0W
0S
0L
0O
0C
0K
0<
b100 (
0D
1@
0>
0H
0F
1P
0M
0N
1X
0U
0V
1`
0]
0^
1h
0e
0f
1p
0m
0n
1x
0u
0v
1""
0}
0~
1*"
0'"
0("
12"
0/"
00"
1:"
07"
08"
1B"
0?"
0@"
1J"
0G"
0H"
1R"
0O"
0P"
1Z"
0W"
0X"
1b"
0_"
0`"
1j"
0g"
0h"
1r"
0o"
0p"
1z"
0w"
0x"
1$#
0!#
0"#
1,#
0)#
0*#
14#
01#
02#
1<#
09#
0:#
1D#
0A#
0B#
1L#
0I#
0J#
1T#
0Q#
0R#
1\#
0Y#
0Z#
1d#
0a#
0b#
b11111111111111111111111111110101 !
b11111111111111111111111111110101 '
1l#
0i#
0j#
09
0A
0I
0Q
0Y
0a
0i
0q
0y
0#"
0+"
03"
0;"
0C"
0K"
0S"
0["
0c"
0k"
0s"
0{"
0%#
0-#
05#
0=#
0E#
0M#
0U#
0]#
0e#
b10 #
b10 %
#280000
0@
0;
b0 (
04
00
0P
0X
0`
0h
0p
0x
0""
0*"
02"
0:"
0B"
0J"
0R"
0Z"
0b"
0j"
0r"
0z"
0$#
0,#
04#
0<#
0D#
0L#
0T#
0\#
0d#
b0 !
b0 '
0l#
05
0*
02
0J
0R
0Z
0b
0j
0r
0z
0$"
0,"
04"
0<"
0D"
0L"
0T"
0\"
0d"
0l"
0t"
0|"
0&#
0.#
06#
0>#
0F#
0N#
0V#
0^#
0f#
01
b0 $
b0 &
b0 #
b0 %
